odoo/addons/mrp_analytic_sale_project/README.rst
odoo/addons/mrp_analytic_sale_project/__init__.py
odoo/addons/mrp_analytic_sale_project/__manifest__.py
odoo/addons/mrp_analytic_sale_project/i18n/it.po
odoo/addons/mrp_analytic_sale_project/i18n/mrp_analytic_sale_project.pot
odoo/addons/mrp_analytic_sale_project/models/__init__.py
odoo/addons/mrp_analytic_sale_project/models/sale_order.py
odoo/addons/mrp_analytic_sale_project/readme/CONTRIBUTORS.rst
odoo/addons/mrp_analytic_sale_project/readme/DESCRIPTION.rst
odoo/addons/mrp_analytic_sale_project/readme/USAGE.rst
odoo/addons/mrp_analytic_sale_project/static/description/icon.png
odoo/addons/mrp_analytic_sale_project/static/description/index.html
odoo/addons/mrp_analytic_sale_project/tests/__init__.py
odoo/addons/mrp_analytic_sale_project/tests/test_sale_analytic.py
odoo14_addon_mrp_analytic_sale_project-14.0.1.0.1.dev7.dist-info/METADATA
odoo14_addon_mrp_analytic_sale_project-14.0.1.0.1.dev7.dist-info/WHEEL
odoo14_addon_mrp_analytic_sale_project-14.0.1.0.1.dev7.dist-info/top_level.txt
odoo14_addon_mrp_analytic_sale_project-14.0.1.0.1.dev7.dist-info/RECORD
